hdlgen/__init__.py
hdlgen/code_gen.py
hdlgen/define.py
hdlgen/py.typed
hdlgen/HDL_Construct/BeginEnd_region.py
hdlgen/HDL_Construct/Generate_region.py
hdlgen/HDL_Construct/IfDef_region.py
hdlgen/HDL_Construct/IfElse_region.py
hdlgen/HDL_Construct/Initial_region.py
hdlgen/HDL_Construct/Logic_region.py
hdlgen/HDL_Construct/Module.py
hdlgen/HDL_Construct/Parameter_region.py
hdlgen/HDL_Construct/Port_region.py
hdlgen/HDL_Construct/Region.py
hdlgen/HDL_Construct/Value.py
hdlgen/HDL_Construct/_Comment.py
hdlgen/HDL_Construct/__init__.py
hdlgen-0.0.1.dist-info/METADATA
hdlgen-0.0.1.dist-info/WHEEL
hdlgen-0.0.1.dist-info/RECORD
