Metadata-Version: 2.4
Name: hdlgen
Version: 0.0.1
Summary: An intuitive Python based HDL code generator for Verilog/SystemVerilog and VHDL.
Author-email: Kelvin Chung <king.chung@manchester.ac.uk>
Requires-Python: >=3.12
